gpnlake/__init__.py
gpnlake/clickhouseclient.py
gpnlake/dfsclient.py
gpnlake/greenplumclient.py
gpnlake-1.0.3.dist-info/licenses/LICENSE
gpnlake-1.0.3.dist-info/METADATA
gpnlake-1.0.3.dist-info/WHEEL
gpnlake-1.0.3.dist-info/top_level.txt
gpnlake-1.0.3.dist-info/RECORD
