Metadata-Version: 2.4
Name: gpnlake
Version: 1.0.3
Summary: Package for exploring datalake
Author-email: petukhova <alexandra.petuhova@gmail.com>
License: The MIT License (MIT)
Classifier: Programming Language :: Python :: 3
Classifier: License :: OSI Approved :: MIT License
Classifier: Operating System :: OS Independent
License-File: LICENSE
Requires-Dist: pysmb>=1.2.11
Requires-Dist: clickhouse-connect>=0.8.18
Requires-Dist: psycopg2-binary>=2.9.10
Requires-Dist: SQLAlchemy>=2.0.41
Requires-Dist: urllib3>=2.5.0
Dynamic: license-file
